{
    "Hiragana": [
        {"character": "あ", "romaji": "A"}, {"character": "い", "romaji": "I"}, {"character": "う", "romaji": "U"},
        {"character": "え", "romaji": "E"}, {"character": "お", "romaji": "O"},
        {"character": "か", "romaji": "KA"}, {"character": "き", "romaji": "KI"}, {"character": "く", "romaji": "KU"},
        {"character": "け", "romaji": "KE"}, {"character": "こ", "romaji": "KO"},
        {"character": "さ", "romaji": "SA"}, {"character": "し", "romaji": "SHI"}, {"character": "す", "romaji": "SU"},
        {"character": "せ", "romaji": "SE"}, {"character": "そ", "romaji": "SO"},
        {"character": "た", "romaji": "TA"}, {"character": "ち", "romaji": "CHI"}, {"character": "つ", "romaji": "TSU"},
        {"character": "て", "romaji": "TE"}, {"character": "と", "romaji": "TO"},
        {"character": "な", "romaji": "NA"}, {"character": "に", "romaji": "NI"}, {"character": "ぬ", "romaji": "NU"},
        {"character": "ね", "romaji": "NE"}, {"character": "の", "romaji": "NO"},
        {"character": "は", "romaji": "HA"}, {"character": "ひ", "romaji": "HI"}, {"character": "ふ", "romaji": "FU"},
        {"character": "へ", "romaji": "HE"}, {"character": "ほ", "romaji": "HO"},
        {"character": "ま", "romaji": "MA"}, {"character": "み", "romaji": "MI"}, {"character": "む", "romaji": "MU"},
        {"character": "め", "romaji": "ME"}, {"character": "も", "romaji": "MO"},
        {"character": "や", "romaji": "YA"}, {"character": "ゆ", "romaji": "YU"}, {"character": "よ", "romaji": "YO"},
        {"character": "ら", "romaji": "RA"}, {"character": "り", "romaji": "RI"}, {"character": "る", "romaji": "RU"},
        {"character": "れ", "romaji": "RE"}, {"character": "ろ", "romaji": "RO"},
        {"character": "わ", "romaji": "WA"}, {"character": "を", "romaji": "WO"}, {"character": "ん", "romaji": "N"},
        {"character": "が", "romaji": "GA"}, {"character": "ぎ", "romaji": "GI"}, {"character": "ぐ", "romaji": "GU"},
        {"character": "げ", "romaji": "GE"}, {"character": "ご", "romaji": "GO"},
        {"character": "ざ", "romaji": "ZA"}, {"character": "じ", "romaji": "JI"}, {"character": "ず", "romaji": "ZU"},
        {"character": "ぜ", "romaji": "ZE"}, {"character": "ぞ", "romaji": "ZO"},
        {"character": "だ", "romaji": "DA"}, {"character": "ぢ", "romaji": "JI"}, {"character": "づ", "romaji": "ZU"},
        {"character": "で", "romaji": "DE"}, {"character": "ど", "romaji": "DO"},
        {"character": "ば", "romaji": "BA"}, {"character": "び", "romaji": "BI"}, {"character": "ぶ", "romaji": "BU"},
        {"character": "べ", "romaji": "BE"}, {"character": "ぼ", "romaji": "BO"},
        {"character": "ぱ", "romaji": "PA"}, {"character": "ぴ", "romaji": "PI"}, {"character": "ぷ", "romaji": "PU"},
        {"character": "ぺ", "romaji": "PE"}, {"character": "ぽ", "romaji": "PO"},
        {"character": "ぎゃ", "romaji": "GYA"}, {"character": "ぎゅ", "romaji": "GYU"}, {"character": "ぎょ", "romaji": "GYO"},
        {"character": "じゃ", "romaji": "JA"}, {"character": "じゅ", "romaji": "JU"}, {"character": "じょ", "romaji": "JO"},
        {"character": "びゃ", "romaji": "BYA"}, {"character": "びゅ", "romaji": "BYU"}, {"character": "びょ", "romaji": "BYO"}
    ],
    "Katakana": [
        {"character": "ア", "romaji": "A"}, {"character": "イ", "romaji": "I"}, {"character": "ウ", "romaji": "U"},
        {"character": "エ", "romaji": "E"}, {"character": "オ", "romaji": "O"},
        {"character": "カ", "romaji": "KA"}, {"character": "キ", "romaji": "KI"}, {"character": "ク", "romaji": "KU"},
        {"character": "ケ", "romaji": "KE"}, {"character": "コ", "romaji": "KO"},
        {"character": "サ", "romaji": "SA"}, {"character": "シ", "romaji": "SHI"}, {"character": "ス", "romaji": "SU"},
        {"character": "セ", "romaji": "SE"}, {"character": "ソ", "romaji": "SO"},
        {"character": "タ", "romaji": "TA"}, {"character": "チ", "romaji": "CHI"}, {"character": "ツ", "romaji": "TSU"},
        {"character": "テ", "romaji": "TE"}, {"character": "ト", "romaji": "TO"},
        {"character": "ナ", "romaji": "NA"}, {"character": "ニ", "romaji": "NI"}, {"character": "ヌ", "romaji": "NU"},
        {"character": "ネ", "romaji": "NE"}, {"character": "ノ", "romaji": "NO"},
        {"character": "ハ", "romaji": "HA"}, {"character": "ヒ", "romaji": "HI"}, {"character": "フ", "romaji": "FU"},
        {"character": "ヘ", "romaji": "HE"}, {"character": "ホ", "romaji": "HO"},
        {"character": "マ", "romaji": "MA"}, {"character": "ミ", "romaji": "MI"}, {"character": "ム", "romaji": "MU"},
        {"character": "メ", "romaji": "ME"}, {"character": "モ", "romaji": "MO"},
        {"character": "ヤ", "romaji": "YA"}, {"character": "ユ", "romaji": "YU"}, {"character": "ヨ", "romaji": "YO"},
        {"character": "ラ", "romaji": "RA"}, {"character": "リ", "romaji": "RI"}, {"character": "ル", "romaji": "RU"},
        {"character": "レ", "romaji": "RE"}, {"character": "ロ", "romaji": "RO"},
        {"character": "ワ", "romaji": "WA"}, {"character": "ヲ", "romaji": "WO"}, {"character": "ン", "romaji": "N"}
    ]
}